pyqode.json-2.10.0-py3.5-nspkg.pth
pyqode/json/__init__.py
pyqode/json/api/__init__.py
pyqode/json/api/folding.py
pyqode/json/modes/__init__.py
pyqode/json/modes/autocomplete.py
pyqode/json/modes/autoindent.py
pyqode/json/modes/linter.py
pyqode/json/modes/sh.py
pyqode/json/panels/__init__.py
pyqode/json/panels/navigation.py
pyqode/json/widgets/__init__.py
pyqode/json/widgets/code_edit.py
pyqode.json-2.10.0.dist-info/DESCRIPTION.rst
pyqode.json-2.10.0.dist-info/METADATA
pyqode.json-2.10.0.dist-info/RECORD
pyqode.json-2.10.0.dist-info/WHEEL
pyqode.json-2.10.0.dist-info/metadata.json
pyqode.json-2.10.0.dist-info/namespace_packages.txt
pyqode.json-2.10.0.dist-info/top_level.txt
