Metadata-Version: 2.0
Name: pyqode.json
Version: 2.10.0
Summary: Adds JSon support to pyqode.core
Home-page: https://github.com/pyQode/pyqode.json
Author: Colin Duquesnoy
Author-email: colin.duquesnoy@gmail.com
License: MIT
Keywords: JSON widget editor
Platform: UNKNOWN
Classifier: Development Status :: 1 - Planning
Classifier: Environment :: X11 Applications :: Qt
Classifier: Environment :: Win32 (MS Windows)
Classifier: Intended Audience :: Developers
Classifier: License :: OSI Approved :: MIT License
Classifier: Operating System :: Microsoft :: Windows
Classifier: Operating System :: POSIX :: Linux
Classifier: Programming Language :: Python :: 2.7
Classifier: Programming Language :: Python :: 3.2
Classifier: Programming Language :: Python :: 3.3
Classifier: Programming Language :: Python :: 3.4
Classifier: Topic :: Software Development :: Libraries :: Application Frameworks
Classifier: Topic :: Software Development :: Widget Sets
Classifier: Topic :: Text Editors :: Integrated Development Environments (IDE)
Requires-Dist: pyqode.core
